Workbook

Sheet MEMÓRIA DE CÁLCULO
A1: PRODUTO | B1: NÃO | D1: METRO | E1: custo real | G1: CLIENTE:
A2: TRILHO DUPLO PARALELO | B2: DUPLO | D2: 20 | G2: Bairro:
A3: TRILHO SIMPLES | B3: SIMPLES | D3: 9 | G3: Cidade:
B4: PAREDE | D4: 8.5 | G4: Fone:
A5: SUPORTE TRILHO PAREDE | B5: SIM | C5: NÃO | D5: 7
A6: DESLIZANTE | D6: 7 | G6: AMBIENTE | L6: AMBIENTE | Q6: AMBIENTE | V6: AMBIENTE | AA6: AMBIENTE | AB6: 5 | AF6: AMBIENTE | AG6: 6 | AK6: AMBIENTE | AL6: 7 | AP6: AMBIENTE | AQ6: 8
A7: TERMINAL | B7: SEM | D7: 5 | G7: MEDIDAS | H7: LARGURA | I7: ALTURA | L7: MEDIDAS | M7: LARGURA | N7: ALTURA | Q7: MEDIDAS | R7: LARGURA | S7: ALTURA | V7: MEDIDAS | W7: LARGURA | X7: ALTURA | AA7: MEDIDAS | AB7: LARGURA | AC7: ALTURA | AF7: MEDIDAS | AG7: LARGURA | AH7: ALTURA | AK7: MEDIDAS | AL7: LARGURA | AM7: ALTURA | AP7: MEDIDAS | AQ7: LARGURA | AR7: ALTURA
A8: BLACKOUT 70% | B8: 0.7 | C8: 0.8 | D8: 19 | E8: 16.61 | I8: 1.8 | N8: 3.83 | S8: 3.83 | X8: 2.5 | AB8: 3.5 | AC8: 2.5 | AG8: 3.5 | AH8: 2.5 | AL8: 3.5 | AM8: 2.5 | AQ8: 3.5 | AR8: 2.5
A9: BLACKOUT 100% | B9: 1 | C9: 0.8 | D9: 25 | E9: 23.74 | G9: MATERIAL | H9: TIPO | I9: VALOR | L9: MATERIAL | M9: TIPO | N9: VALOR | Q9: MATERIAL | R9: TIPO | S9: VALOR | V9: MATERIAL | W9: TIPO | X9: VALOR | AA9: MATERIAL | AB9: TIPO | AC9: VALOR | AF9: MATERIAL | AG9: TIPO | AH9: VALOR | AK9: MATERIAL | AL9: TIPO | AM9: VALOR | AP9: MATERIAL | AQ9: TIPO | AR9: VALOR
A10: TECIDO VOIL | B10: LINHO RUSTICO | C10: 3 | D10: 17
A11: TECIDO LINHO | B11: LINHO | C11: 3 | D11: 15 | G11: TRILHO | H11: DUPLO | I11: =IF(H11=$B$2,SUM(H8*$D$2),IF(H11=$B$3,SUM(H8*$D$3),IF(H11=$B$4,SUM(H8*$D$4),0))) -> 0 | L11: TRILHO | M11: DUPLO | N11: =IF(M11=$B$2,SUM(M8*$D$2),IF(M11=$B$3,SUM(M8*$D$3),IF(M11=$B$4,SUM(M8*$D$4),0))) -> 0 | Q11: TRILHO | R11: DUPLO | S11: =IF(R11=$B$2,SUM(R8*$D$2),IF(R11=$B$3,SUM(R8*$D$3),IF(R11=$B$4,SUM(R8*$D$4),0))) -> 0 | V11: TRILHO | W11: DUPLO | X11: =IF(W11=$B$2,SUM(W8*$D$2),IF(W11=$B$3,SUM(W8*$D$3),IF(W11=$B$4,SUM(W8*$D$4),0))) -> 0 | AA11: TRILHO | AB11: NÃO | AC11: =IF(AB11=$B$2,SUM(AB8*$D$2),IF(AB11=$B$3,SUM(AB8*$D$3),IF(AB11=$B$4,SUM(AB8*$D$4),0))) -> 0 | AF11: TRILHO | AG11: NÃO | AH11: =IF(AG11=$B$2,SUM(AG8*$D$2),IF(AG11=$B$3,SUM(AG8*$D$3),IF(AG11=$B$4,SUM(AG8*$D$4),0))) -> 0 | AK11: TRILHO | AL11: NÃO | AM11: =IF(AL11=$B$2,SUM(AL8*$D$2),IF(AL11=$B$3,SUM(AL8*$D$3),IF(AL11=$B$4,SUM(AL8*$D$4),0))) -> 0 | AP11: TRILHO | AQ11: NÃO | AR11: =IF(AQ11=$B$2,SUM(AQ8*$D$2),IF(AQ11=$B$3,SUM(AQ8*$D$3),IF(AQ11=$B$4,SUM(AQ8*$D$4),0))) -> 0
A12: TECIDO NÃO | B12: NÃO | D12: 0 | G12: SUPORTE PAREDE | H12: NÃO | I12: =IF(H12="SIM",H8*$D$5,0) -> 0 | L12: SUPORTE PAREDE | M12: NÃO | N12: =IF(M12="SIM",M8*$D$5,0) -> 0 | Q12: SUPORTE PAREDE | R12: NÃO | S12: =IF(R12="SIM",R8*$D$5,0) -> 0 | V12: SUPORTE PAREDE | W12: NÃO | X12: =IF(W12="SIM",W8*$D$5,0) -> 0 | AA12: SUPORTE PAREDE | AB12: NÃO | AC12: =IF(AB12="SIM",AB8*$D$5,0) -> 0 | AF12: SUPORTE PAREDE | AG12: NÃO | AH12: =IF(AG12="SIM",AG8*$D$5,0) -> 0 | AK12: SUPORTE PAREDE | AL12: NÃO | AM12: =IF(AL12="SIM",AL8*$D$5,0) -> 0 | AP12: SUPORTE PAREDE | AQ12: NÃO | AR12: =IF(AQ12="SIM",AQ8*$D$5,0) -> 0
A13: CONF. EI | B13: WAVE | D13: 76 | G13: DESLIZANTE | H13: SIM | I13: =IF(H13="SIM",H8*$D$6,0) -> 0 | L13: DESLIZANTE | M13: SIM | N13: =IF(M13="SIM",M8*$D$6,0) -> 0 | Q13: DESLIZANTE | R13: SIM | S13: =IF(R13="SIM",R8*$D$6,0) -> 0 | V13: DESLIZANTE | W13: SIM | X13: =IF(W13="SIM",W8*$D$6,0) -> 0 | AA13: DESLIZANTE | AB13: NÃO | AC13: =IF(AB13="SIM",AB8*$D$6,0) -> 0 | AF13: DESLIZANTE | AG13: NÃO | AH13: =IF(AG13="SIM",AG8*$D$6,0) -> 0 | AK13: DESLIZANTE | AL13: NÃO | AM13: =IF(AL13="SIM",AL8*$D$6,0) -> 0 | AP13: DESLIZANTE | AQ13: NÃO | AR13: =IF(AQ13="SIM",AQ8*$D$6,0) -> 0
A14: CONF. PA | B14: PA | D14: 76 | G14: TERMINAL | H14: SIM | I14: =IF(H14="SIM",H8*$D$7,0) -> 0 | L14: TERMINAL | M14: SIM | N14: =IF(M14="SIM",M8*$D$7,0) -> 0 | Q14: TERMINAL | R14: SIM | S14: =IF(R14="SIM",R8*$D$7,0) -> 0 | V14: TERMINAL | W14: SIM | X14: =IF(W14="SIM",W8*$D$7,0) -> 0 | AA14: TERMINAL | AB14: NÃO | AC14: =IF(AB14="SIM",AB8*$D$7,0) -> 0 | AF14: TERMINAL | AG14: NÃO | AH14: =IF(AG14="SIM",AG8*$D$7,0) -> 0 | AK14: TERMINAL | AL14: NÃO | AM14: =IF(AL14="SIM",AL8*$D$7,0) -> 0 | AP14: TERMINAL | AQ14: NÃO | AR14: =IF(AQ14="SIM",AQ8*$D$7,0) -> 0
A15: CONF. NÃO | B15: NÃO | D15: 0 | G15: BLACKOUT | H15: 0.7 | I15: =IF(H15=$B$9,SUM((H8+$C$9)*$D$9),IF(H15=$B$8,SUM((H8+$C$8)*$D$8),0)) -> 15.2 | L15: BLACKOUT | M15: SEM | N15: =IF(M15=$B$9,SUM((M8+$C$9)*$D$9),IF(M15=$B$8,SUM((M8+$C$8)*$D$8),0)) -> 0 | Q15: BLACKOUT | R15: SEM | S15: =IF(R15=$B$9,SUM((R8+$C$9)*$D$9),IF(R15=$B$8,SUM((R8+$C$8)*$D$8),0)) -> 0 | V15: BLACKOUT | W15: SEM | X15: =IF(W15=$B$9,SUM((W8+$C$9)*$D$9),IF(W15=$B$8,SUM((W8+$C$8)*$D$8),0)) -> 0 | AA15: BLACKOUT | AB15: SEM | AC15: =IF(AB15=$B$9,SUM((AB8+$C$9)*$D$9),IF(AB15=$B$8,SUM((AB8+$C$8)*$D$8),0)) -> 0 | AF15: BLACKOUT | AG15: SEM | AH15: =IF(AG15=$B$9,SUM((AG8+$C$9)*$D$9),IF(AG15=$B$8,SUM((AG8+$C$8)*$D$8),0)) -> 0 | AK15: BLACKOUT | AL15: SEM | AM15: =IF(AL15=$B$9,SUM((AL8+$C$9)*$D$9),IF(AL15=$B$8,SUM((AL8+$C$8)*$D$8),0)) -> 0 | AP15: BLACKOUT | AQ15: SEM | AR15: =IF(AQ15=$B$9,SUM((AQ8+$C$9)*$D$9),IF(AQ15=$B$8,SUM((AQ8+$C$8)*$D$8),0)) -> 0
A16: INSTALAÇÃO NÃO | B16: NÃO | D16: 0 | G16: TECIDO | H16: LINHO | I16: =IF(H16=$B$11,SUM((H8*$C$11)*$D$11),IF(H16=$B$10,SUM((H8*C10)*D10),0)) -> 0 | L16: TECIDO | M16: LINHO | N16: =IF(M16=$B$11,SUM((M8*$C$11)*$D$11),IF(M16=$B$10,SUM((M8*H10)*I10),0)) -> 0 | Q16: TECIDO | R16: LINHO | S16: =IF(R16=$B$11,SUM((R8*$C$11)*$D$11),IF(R16=$B$10,SUM((R8*M10)*N10),0)) -> 0 | V16: TECIDO | W16: LINHO | X16: =IF(W16=$B$11,SUM((W8*$C$11)*$D$11),IF(W16=$B$10,SUM((W8*M10)*N10),0)) -> 0 | AA16: TECIDO | AB16: NÃO | AC16: =IF(AB16=$B$11,SUM((AB8*$C$11)*$D$11),IF(AB16=$B$10,SUM((AB8*R10)*S10),0)) -> 0 | AF16: TECIDO | AG16: NÃO | AH16: =IF(AG16=$B$11,SUM((AG8*$C$11)*$D$11),IF(AG16=$B$10,SUM((AG8*W10)*X10),0)) -> 0 | AK16: TECIDO | AL16: NÃO | AM16: =IF(AL16=$B$11,SUM((AL8*$C$11)*$D$11),IF(AL16=$B$10,SUM((AL8*AB10)*AC10),0)) -> 0 | AP16: TECIDO | AQ16: NÃO | AR16: =IF(AQ16=$B$11,SUM((AQ8*$C$11)*$D$11),IF(AQ16=$B$10,SUM((AQ8*AG10)*AH10),0)) -> 0
A17: INTALAÇAO | B17: INTALAÇAO | D17: 40 | G17: PREGAS | H17: WAVE | I17: =IF(H17=$B$14,SUM(H8*$D$14),IF(H17=$B$13,SUM(H8*$D$13),0)) -> 0 | L17: PREGAS | M17: WAVE | N17: =IF(M17=$B$14,SUM(M8*$D$14),IF(M17=$B$13,SUM(M8*$D$13),0)) -> 0 | Q17: PREGAS | R17: WAVE | S17: =IF(R17=$B$14,SUM(R8*$D$14),IF(R17=$B$13,SUM(R8*$D$13),0)) -> 0 | V17: PREGAS | W17: WAVE | X17: =IF(W17=$B$14,SUM(W8*$D$14),IF(W17=$B$13,SUM(W8*$D$13),0)) -> 0 | AA17: PREGAS | AB17: NÃO | AC17: =IF(AB17=$B$14,SUM(AB8*$D$14),IF(AB17=$B$13,SUM(AB8*$D$13),0)) -> 0 | AF17: CONFECÇÃO | AG17: NÃO | AH17: =IF(AG17=$B$14,SUM(AG8*$D$14),IF(AG17=$B$13,SUM(AG8*$D$13),0)) -> 0 | AK17: CONFECÇÃO | AL17: NÃO | AM17: =IF(AL17=$B$14,SUM(AL8*$D$14),IF(AL17=$B$13,SUM(AL8*$D$13),0)) -> 0 | AP17: CONFECÇÃO | AQ17: NÃO | AR17: =IF(AQ17=$B$14,SUM(AQ8*$D$14),IF(AQ17=$B$13,SUM(AQ8*$D$13),0)) -> 0
A18: DESLOCAMENTO | B18: DESLOCAMENTO | D18: 60 | G18: INSTALAÇÃO | H18: SIM | I18: =IF(H18="SIM",SUM(H8*$D$17,),0) -> 0 | L18: INSTALAÇÃO | M18: SIM | N18: =IF(M18="SIM",SUM(M8*$D$17,),0) -> 0 | Q18: INSTALAÇÃO | R18: SIM | S18: =IF(R18="SIM",SUM(R8*$D$17,),0) -> 0 | V18: INSTALAÇÃO | W18: SIM | X18: =IF(W18="SIM",SUM(W8*$D$17,),0) -> 0 | AA18: INSTALAÇÃO | AB18: NÃO | AC18: =IF(AB18="SIM",SUM(AB8*$D$17,),0) -> 0 | AF18: INSTALAÇÃO | AG18: NÃO | AH18: =IF(AG18="SIM",SUM(AG8*$D$17,),0) -> 0 | AK18: INSTALAÇÃO | AL18: NÃO | AM18: =IF(AL18="SIM",SUM(AL8*$D$17,),0) -> 0 | AP18: INSTALAÇÃO | AQ18: NÃO | AR18: =IF(AQ18="SIM",SUM(AQ8*$D$17,),0) -> 0
G19: DESLOCAMENTO | H19: NÃO
A20: ADICIONAL DE TECIDO
A21: BLACKOUT 70% | B21: 0.7 | D21: 0.8
A22: BLACKOUT 100% | B22: 1 | D22: 0.8 | G22: TOTAL CUSTO | H22: VALOR TOTAL | L22: TOTAL CUSTO | M22: VALOR TOTAL | Q22: TOTAL CUSTO | R22: VALOR TOTAL | V22: TOTAL CUSTO | W22: VALOR TOTAL | AA22: TOTAL CUSTO | AB22: VALOR TOTAL | AF22: TOTAL CUSTO | AG22: VALOR TOTAL | AK22: TOTAL CUSTO | AL22: VALOR TOTAL | AP22: TOTAL CUSTO | AQ22: VALOR TOTAL
A23: LINHO | B23: LINHO | D23: 3 | G23: CUSTO | H23: =SUM(I11:I19) -> 15.2 | L23: CUSTO | M23: =SUM(N11:N19) -> 0 | Q23: CUSTO | R23: =SUM(S11:S19) -> 0 | V23: CUSTO | W23: =SUM(X11:X19) -> 0 | AA23: CUSTO | AB23: =SUM(AC11:AC19) -> 0 | AF23: CUSTO | AG23: =SUM(AH11:AH19) -> 0 | AK23: CUSTO | AL23: =SUM(AM11:AM19) -> 0 | AP23: CUSTO | AQ23: =SUM(AR11:AR19) -> 0
G24: LUCRO | H24: 1 | L24: LUCRO | M24: 1 | Q24: LUCRO | R24: 1 | V24: LUCRO | W24: 1 | AA24: LUCRO | AB24: 1 | AF24: LUCRO | AG24: 1.1 | AK24: LUCRO | AL24: 1.1 | AP24: LUCRO | AQ24: 1.1
A25: LOCAL
A26: CIDADE | B26: OUTRO | C26: VITÓRIA/GUARAPARI | D26: VV | E26: NÃO | G26: TOTAL VENDA | H26: VALOR | I26: PARCELAS | J26: PARCELA | L26: TOTAL VENDA | M26: VALOR | N26: PARCELAS | O26: PARCELA | Q26: TOTAL VENDA | R26: VALOR | S26: PARCELAS | T26: PARCELA | V26: TOTAL VENDA | W26: VALOR | X26: PARCELAS | Y26: PARCELA | AA26: TOTAL VENDA | AB26: VALOR | AC26: PARCELAS | AD26: PARCELA | AF26: TOTAL VENDA | AG26: VALOR | AH26: PARCELAS | AI26: PARCELA | AK26: TOTAL VENDA | AL26: VALOR | AM26: PARCELAS | AN26: PARCELA | AP26: TOTAL VENDA | AQ26: VALOR | AR26: PARCELAS
B27: 1.5 | C27: 1 | D27: 0.5 | G27: TOTAL VENDA | H27: =(H23*H24)+H23 -> 30.4 | I27: 10 | J27: =H27/I27 -> 3.04 | L27: TOTAL VENDA | M27: =(M23*M24)+M23 -> 0 | N27: 10 | O27: =M27/N27 -> 0 | Q27: TOTAL VENDA | R27: =(R23*R24)+R23 -> 0 | S27: 10 | T27: =R27/S27 -> 0 | V27: TOTAL VENDA | W27: =(W23*W24)+W23 -> 0 | X27: 10 | Y27: =W27/X27 -> 0 | AA27: TOTAL VENDA | AB27: =(AB23*AB24)+AB23 -> 0 | AC27: 10 | AD27: =AB27/AC27 -> 0 | AF27: TOTAL VENDA | AG27: =(AG23*AG24)+AG23 -> 0 | AH27: 10 | AI27: =AG27/AH27 -> 0 | AK27: TOTAL VENDA | AL27: =(AL23*AL24)+AL23 -> 0 | AM27: 10 | AN27: =AL27/AM27 -> 0 | AP27: TOTAL VENDA | AQ27: =(AQ23*AQ24)+AQ23 -> 0 | AR27: 10
G28: PROMOCIONAL 20% | H28: =H27*0.8 -> 24.32 | I28: 1 | J28: =H28/I28 -> 24.32 | L28: PROMOCIONAL 20% | M28: =M27*0.8 -> 0 | N28: 1 | O28: =M28/N28 -> 0 | Q28: PROMOCIONAL 20% | R28: =R27*0.8 -> 0 | S28: 1 | T28: =R28/S28 -> 0 | V28: PROMOCIONAL 20% | W28: =W27*0.8 -> 0 | X28: 1 | Y28: =W28/X28 -> 0 | AA28: PROMOCIONAL 20% | AB28: =AB27*0.8 -> 0 | AC28: 1 | AD28: =AB28/AC28 -> 0 | AF28: PROMOCIONAL 20% | AG28: =AG27*0.8 -> 0 | AH28: 1 | AI28: =AG28/AH28 -> 0 | AK28: PROMOCIONAL 20% | AL28: =AL27*0.8 -> 0 | AM28: 1 | AN28: =AL28/AM28 -> 0 | AP28: PROMOCIONAL 20% | AQ28: =AQ27*0.8 -> 0 | AR28: 1
G29: PROMOCIONAL 10% | H29: =H27*0.9 -> 27.36 | I29: 3 | J29: =H29/I29 -> 9.12 | L29: PROMOCIONAL 10% | M29: =M27*0.9 -> 0 | N29: 3 | O29: =M29/N29 -> 0 | Q29: PROMOCIONAL 10% | R29: =R27*0.9 -> 0 | S29: 3 | T29: =R29/S29 -> 0 | V29: PROMOCIONAL 10% | W29: =W27*0.9 -> 0 | X29: 3 | Y29: =W29/X29 -> 0 | AA29: PROMOCIONAL 10% | AB29: =AB27*0.9 -> 0 | AC29: 3 | AD29: =AB29/AC29 -> 0 | AF29: PROMOCIONAL 10% | AG29: =AG27*0.9 -> 0 | AH29: 3 | AI29: =AG29/AH29 -> 0 | AK29: PROMOCIONAL 10% | AL29: =AL27*0.9 -> 0 | AM29: 3 | AN29: =AL29/AM29 -> 0 | AP29: PROMOCIONAL 10% | AQ29: =AQ27*0.9 -> 0 | AR29: 3
H31: TAXA CARTÃO % | I31: TAXA CARTÃO VALOR | J31: LUCRO | M31: TAXA CARTÃO % | N31: TAXA CARTÃO VALOR | O31: LUCRO | R31: TAXA CARTÃO % | S31: TAXA CARTÃO VALOR | T31: LUCRO | W31: TAXA CARTÃO % | X31: TAXA CARTÃO VALOR | Y31: LUCRO | AB31: TAXA CARTÃO % | AC31: TAXA CARTÃO VALOR | AD31: LUCRO | AG31: TAXA CARTÃO % | AH31: TAXA CARTÃO VALOR | AI31: LUCRO | AL31: TAXA CARTÃO % | AM31: TAXA CARTÃO VALOR | AN31: LUCRO | AQ31: TAXA CARTÃO % | AR31: TAXA CARTÃO VALOR
G32: À VISTA - 20% | J32: =H28-H23 -> 9.12 | L32: À VISTA - 20% | O32: =M28-M23 -> 0 | Q32: À VISTA - 20% | T32: =R28-R23 -> 0 | V32: À VISTA - 20% | Y32: =W28-W23 -> 0 | AA32: À VISTA - 20% | AD32: =AB28-AB23 -> 0 | AF32: À VISTA - 20% | AI32: =AG28-AG23 -> 0 | AK32: À VISTA - 20% | AN32: =AL28-AL23 -> 0 | AP32: À VISTA - 20%
G33: TAXA CARTÃO 3X - 10% | H33: 0.0619 | I33: =H29*H33 -> 1.693584 | J33: =H29-H23-I33 -> 10.466416 | L33: TAXA CARTÃO 3X - 10% | M33: 0.0619 | N33: =M29*M33 -> 0 | O33: =M29-M23-N33 -> 0 | Q33: TAXA CARTÃO 3X - 10% | R33: 0.0619 | S33: =R29*R33 -> 0 | T33: =R29-R23-S33 -> 0 | V33: TAXA CARTÃO 3X - 10% | W33: 0.0619 | X33: =W29*W33 -> 0 | Y33: =W29-W23-X33 -> 0 | AA33: TAXA CARTÃO 3X - 10% | AB33: 0.0619 | AC33: =AB29*AB33 -> 0 | AD33: =AB29-AB23-AC33 -> 0 | AF33: TAXA CARTÃO 3X - 10% | AG33: 0.0619 | AH33: =AG29*AG33 -> 0 | AI33: =AG29-AG23-AH33 -> 0 | AK33: TAXA CARTÃO 3X - 10% | AL33: 0.0619 | AM33: =AL29*AL33 -> 0 | AN33: =AL29-AL23-AM33 -> 0 | AP33: TAXA CARTÃO 3X - 10% | AQ33: 0.0619 | AR33: =AQ29*AQ33 -> 0
G34: TAXA CARTÃO 10X | H34: 0.1149 | I34: =H27*H34 -> 3.49296 | J34: =H27-H23-I34 -> 11.70704 | L34: TAXA CARTÃO 10X | M34: 0.1149 | N34: =M27*M34 -> 0 | O34: =M27-M23-N34 -> 0 | Q34: TAXA CARTÃO 10X | R34: 0.1149 | S34: =R27*R34 -> 0 | T34: =R27-R23-S34 -> 0 | V34: TAXA CARTÃO 10X | W34: 0.1149 | X34: =W27*W34 -> 0 | Y34: =W27-W23-X34 -> 0 | AA34: TAXA CARTÃO 10X | AB34: 0.1149 | AC34: =AB27*AB34 -> 0 | AD34: =AB27-AB23-AC34 -> 0 | AF34: TAXA CARTÃO 10X | AG34: 0.1149 | AH34: =AG27*AG34 -> 0 | AI34: =AG27-AG23-AH34 -> 0 | AK34: TAXA CARTÃO 10X | AL34: 0.1149 | AM34: =AL27*AL34 -> 0 | AN34: =AL27-AL23-AM34 -> 0 | AP34: TAXA CARTÃO 10X | AQ34: 0.1149 | AR34: =AQ27*AQ34 -> 0

Sheet ORÇAMENTO
A1: Roses Decor | B1: =CONCATENATE('MEMÓRIA DE CÁLCULO'!G5," ",'MEMÓRIA DE CÁLCULO'!H5)
A3: Cliente: | B3: ='MEMÓRIA DE CÁLCULO'!H1 -> 0
A4: Bairro: | B4: ='MEMÓRIA DE CÁLCULO'!H2 -> 0
A5: Cidade: | B5: ='MEMÓRIA DE CÁLCULO'!H3 -> 0
A6: Fone: | B6: ='MEMÓRIA DE CÁLCULO'!H4 -> 0
A7: Data do Orçamento: | B7: =TODAY() -> 45768
A9: AMBIENTE | B9: DESCRIÇÃO | C9: VALOR TOTAL
A10: AMBIENTE
A11: ='MEMÓRIA DE CÁLCULO'!H6 -> 0 | B11: =CONCATENATE('MEMÓRIA DE CÁLCULO'!G11," ",'MEMÓRIA DE CÁLCULO'!H11," - ",'MEMÓRIA DE CÁLCULO'!G15," "," - ",'MEMÓRIA DE CÁLCULO'!G16," ",'MEMÓRIA DE CÁLCULO'!H16," - ",'MEMÓRIA DE CÁLCULO'!G17," ",'MEMÓRIA DE CÁLCULO'!H17) -> TRILHO DUPLO - BLACKOUT - TECIDO LINHO - PREGAS WAVE | C11: ='MEMÓRIA DE CÁLCULO'!H27 -> 30.4
A12: ='MEMÓRIA DE CÁLCULO'!M6 -> 0 | B12: =CONCATENATE('MEMÓRIA DE CÁLCULO'!L11," ",'MEMÓRIA DE CÁLCULO'!M11," - ",'MEMÓRIA DE CÁLCULO'!L15," "," - ",'MEMÓRIA DE CÁLCULO'!L16," ",'MEMÓRIA DE CÁLCULO'!M16," - ",'MEMÓRIA DE CÁLCULO'!L17," ",'MEMÓRIA DE CÁLCULO'!H17) -> TRILHO DUPLO - BLACKOUT - TECIDO LINHO - PREGAS WAVE | C12: ='MEMÓRIA DE CÁLCULO'!M27 -> 0
A13: ='MEMÓRIA DE CÁLCULO'!R6 -> 0 | B13: =CONCATENATE('MEMÓRIA DE CÁLCULO'!Q11," ",'MEMÓRIA DE CÁLCULO'!R11," - ",'MEMÓRIA DE CÁLCULO'!Q15," "," - ",'MEMÓRIA DE CÁLCULO'!Q16," ",'MEMÓRIA DE CÁLCULO'!R16," - ",'MEMÓRIA DE CÁLCULO'!Q17," ",'MEMÓRIA DE CÁLCULO'!R17) -> TRILHO DUPLO - BLACKOUT - TECIDO LINHO - PREGAS WAVE | C13: ='MEMÓRIA DE CÁLCULO'!R27 -> 0
A14: ='MEMÓRIA DE CÁLCULO'!W6 -> 0 | B14: =CONCATENATE('MEMÓRIA DE CÁLCULO'!L11," ",'MEMÓRIA DE CÁLCULO'!M11," - ",'MEMÓRIA DE CÁLCULO'!L15," "," - ",'MEMÓRIA DE CÁLCULO'!L16," ",'MEMÓRIA DE CÁLCULO'!M16," - ",'MEMÓRIA DE CÁLCULO'!L17," ",'MEMÓRIA DE CÁLCULO'!H17) -> TRILHO DUPLO - BLACKOUT - TECIDO LINHO - PREGAS WAVE | C14: ='MEMÓRIA DE CÁLCULO'!W27 -> 0
A15: ='MEMÓRIA DE CÁLCULO'!AB6 -> 5 | B15: =CONCATENATE('MEMÓRIA DE CÁLCULO'!V11," ",'MEMÓRIA DE CÁLCULO'!W11," - ",'MEMÓRIA DE CÁLCULO'!V15," "," - ",'MEMÓRIA DE CÁLCULO'!V16," ",'MEMÓRIA DE CÁLCULO'!W16," - ",'MEMÓRIA DE CÁLCULO'!V17," ",'MEMÓRIA DE CÁLCULO'!W17) -> TRILHO DUPLO - BLACKOUT - TECIDO LINHO - PREGAS WAVE | C15: ='MEMÓRIA DE CÁLCULO'!AB27 -> 0
A16: TOTAL | C16: =SUM(C11:C15) -> 30.4
A17: DESCONTO PROMOCIONAL | C17: 0.2
A18: TOTAL COM DESCONTO: 50% PEDIDO / 50% ENTREGA | C18: =C16-(C16*C17) -> 24.32
A19: CONDIÇÕES DA VENDA
A20: PRAZO DE ENTREGA | B20: 20 DIAS
A21: INSTALAÇÃO: | B21: INCLUSA NO VALOR
B22: PARCELAMENTO NÃO INCLUI DESCONTO DE 20%
A24: Orçamento sujeito a alteração devida medidas e padrões/tecidos
A25: OPÇÕES DE PAGAMENTO:
A26: Total do Desconto | B26: Forma de Pagamento | C26: Valor da Parcela
A27: DESCONTO 20% | B27: A VISTA | C27: =C18 -> 24.32
A28: DESCONTO 10% | B28: CARTÃO DE CRÉDITO (3X) | C28: =(C16*0.9)/3 -> 9.12
A29: 10X SEM JUROS | B29: CARTÃO DE CRÉDITO (10X) | C29: =C16/10 -> 3.04
